evokernel/__init__.py
evokernel/cli.py
evokernel/cuda/__init__.py
evokernel/cuda/context.py
evokernel/cuda/parser.py
evokernel/dashboard/__init__.py
evokernel/dashboard/server.py
evokernel/dashboard/templates/dashboard.html
evokernel/docs/.gitkeep
evokernel/docs/chunks.jsonl
evokernel/docs/embeddings.npy
evokernel/evaluators/__init__.py
evokernel/evaluators/base.py
evokernel/evaluators/templates/local_standalone.py.j2
evokernel/evaluators/templates/local_task.py.j2
evokernel/evaluators/templates/modal_standalone.py.j2
evokernel/evaluators/templates/modal_task.py.j2
evokernel/modal/__init__.py
evokernel/modal/app.py
evokernel/modal/client.py
evokernel/openevolve_integration/__init__.py
evokernel/openevolve_integration/config.py
evokernel/openevolve_integration/runner.py
evokernel/prompts.py
evokernel/task_catalog.json
evokernel/tools/__init__.py
evokernel/tools/analyze.py
evokernel/tools/apply.py
evokernel/tools/compare.py
evokernel/tools/docs.py
evokernel/tools/evolve.py
evokernel/tools/explain.py
evokernel/tools/hardware.py
evokernel/tools/mark.py
evokernel/tools/profile.py
evokernel/tools/show.py
evokernel/tools/status.py
gptme/__init__.py
gptme/__main__.py
gptme/__version__.py
gptme/acp/__init__.py
gptme/acp/__main__.py
gptme/acp/adapter.py
gptme/acp/agent.py
gptme/acp/types.py
gptme/chat.py
gptme/cli.py
gptme/codeblock.py
gptme/commands/__init__.py
gptme/commands/base.py
gptme/commands/export.py
gptme/commands/llm.py
gptme/commands/meta.py
gptme/commands/session.py
gptme/config.py
gptme/constants.py
gptme/context/__init__.py
gptme/context/adaptive_compressor.py
gptme/context/compress.py
gptme/context/config.py
gptme/context/selector/__init__.py
gptme/context/selector/base.py
gptme/context/selector/config.py
gptme/context/selector/file_config.py
gptme/context/selector/file_integration.py
gptme/context/selector/file_selector.py
gptme/context/selector/hybrid.py
gptme/context/selector/llm_based.py
gptme/context/selector/rule_based.py
gptme/context/task_analyzer.py
evokernel-0.8.0.dist-info/METADATA
evokernel-0.8.0.dist-info/WHEEL
evokernel-0.8.0.dist-info/entry_points.txt
evokernel-0.8.0.dist-info/RECORD
